setup.py
gopress/__init__.py
gopress.egg-info/PKG-INFO
gopress.egg-info/SOURCES.txt
gopress.egg-info/dependency_links.txt
gopress.egg-info/not-zip-safe
gopress.egg-info/top_level.txt