Metadata-Version: 1.0
Name: gopress
Version: 0.3
Summary: Module to scrape gopress.be website
Home-page: http://github.com/exergos/gopress-scrape
Author: Exergos
Author-email: info@exergos.be
License: MIT
Platform: UNKNOWN
